{"chunk_definitions":[{"chunk_id":"cabllv09d5n65","expansion_state":0,"options":[],"row":12,"row_count":1,"visible":true},{"chunk_id":"cto666h7wbka5","expansion_state":0,"options":[],"row":23,"row_count":1,"visible":true},{"chunk_id":"c234esgr8mjo9","expansion_state":0,"options":[],"row":34,"row_count":1,"visible":true},{"chunk_id":"cjfamw9a9ulsp","expansion_state":0,"options":[],"row":46,"row_count":1,"visible":true},{"chunk_id":"cy569d1y21zys","expansion_state":0,"options":[],"row":55,"row_count":1,"visible":true},{"chunk_id":"c85hpu7qjgstv","expansion_state":0,"options":[],"row":59,"row_count":1,"visible":true},{"chunk_id":"c4xeptc1vtjlc","expansion_state":0,"options":[],"row":62,"row_count":1,"visible":true},{"chunk_id":"cncozrl7hs92d","expansion_state":0,"options":[],"row":65,"row_count":1,"visible":true}],"doc_write_time":1686105139.0374}
